<?xml version="1.0" encoding="UTF-8"?>
<!--Copyright 2021 The MathWorks, Inc.-->

<rsccat xmlns:xsi="http://www.w3.org/2001/XMLSchema-instance" version="1.0" locale="ko_KR" product="MATLAB" xsi:noNamespaceSchemaLocation="../../resources/schema/msgcat.xsd">
  <message>
    <entry key="CreateFromNonFigure">Figure가 아닌 핸들에서 Figure를 생성할 수 없습니다.</entry>
    <entry key="InputMustBeAFigureHandle">단일 입력값은 기존 Figure 핸들이거나 1에서 2147483646 사이의 정수 스칼라여야 합니다.</entry>
    <entry key="numargs">인수의 개수가 올바르지 않음</entry>
  </message>
</rsccat>
