<?xml version="1.0" encoding="utf-8"?>
<!-- Copyright 2012 The MathWorks, Inc. -->
<rsccat locale="en_US" product="MATLAB" version="1.0">
   <message>
      <entry key="Close">Close</entry>
      <entry key="ColumnNumber">Column number</entry>
      <entry key="DescriptiveStatistics">Descriptive Statistics</entry>
      <entry key="DescriptiveStatisticsSummary">Descriptive statistics summary for selected time series</entry>
      <entry key="Help">Help</entry>
      <entry key="Mean">Mean</entry>
      <entry key="Median">Median</entry>
      <entry key="Max">Max</entry>
      <entry key="Min">Min</entry>
      <entry key="NumberOfColumns">Number of Columns</entry>
      <entry key="Path">Path</entry>
      <entry key="SelectTimeSeries">Select time series</entry>
      <entry key="STD" translate="false" note="TranslateFalseBatch;">STD</entry>
      <entry key="TimeSeries">Time Series</entry>
   </message>
</rsccat>