<?xml version="1.0" encoding="UTF-8"?>
<!--Copyright 2021 The MathWorks, Inc.-->

<rsccat xmlns:xsi="http://www.w3.org/2001/XMLSchema-instance" version="1.0" locale="ja_JP" product="MATLAB" xsi:noNamespaceSchemaLocation="../../resources/schema/msgcat.xsd">
  <message>
    <entry key="BadCurrentAxesHandle">タイプ {0} のハンドルを現在の Axes にすることはできません。</entry>
    <entry key="DeletedHandle">削除されたハンドルを現在の Axes にすることはできません。</entry>
    <entry key="BadCurrentAxesInvalidChildHandle">Axes は Figure の既存の子でなければなりません。</entry>
    <entry key="BadCurrentPoint">CurrentPoint 値が大きすぎます。</entry>
    <entry key="CannotSetNormalizedPaperSize">PaperSize は正規化された PaperUnits では設定できません。\nPaperSize を設定するには次のようにします。\nPaperType を別の値に設定する、または \nPaperUnits をインチ、センチメートルまたはポイントに変更してから、PaperSize を設定する。</entry>
    <entry key="ColormapIntensityRange">すべてのカラー マップの強度は、0 と 1 の間でなければなりません。</entry>
    <entry key="ColormapNumericType">カラーマップは、double、float、sparse のいずれかのタイプの配列でなければなりません。</entry>
    <entry key="ColormapRGBDimension">カラーマップは、RGB 色強度の M 行 3 列の配列でなければなりません。</entry>
    <entry key="CreatePeerWindow">Figure ウィンドウに対し Java Peer を作成できませんでした。</entry>
    <entry key="CurrentAxesChild">Axes は Figure の既存の子でなければなりません。</entry>
    <entry key="CurrentAxesHandle">引数は、有効な Axes ハンドルでなければなりません。</entry>
    <entry key="DefaultBar">既定の {0} が作成できません。</entry>
    <entry key="DragRect">ドラッグ四角形には、{0,number,integer} 列ではなく 4 列が必要です。</entry>
    <entry key="FigureSavedToMATFile">Figure を {0} に保存しました。グラフィックス ハンドル変数を保存すると、非常に大きいファイルが作成される場合があります。グラフィックスの Figure を保存するには、&lt;a href=\"matlab:helpview([docroot,''/techdoc/ref/savefig.html''])\"&gt;savefig&lt;/a&gt; を使用します。</entry>
    <entry key="HandleAssignment">Figure ハンドルの割り当てに失敗しました。</entry>
    <entry key="HandleInUse">要求された Figure ハンドルは別のオブジェクトで使用中です。</entry>
    <entry key="Hittest">Figure ハンドルが必要です。</entry>
    <entry key="IncorrectWindowStyle">MATLAB が表示なしで起動している場合や -noFigureWindows オプションが指定されている場合、WindowStyle を ''docked'' に設定することはできません。</entry>
    <entry key="IntegerHandle">単入力は、既存の Figure ハンドルか、1 から {0,number,integer} までのスカラーの整数でなければなりません。</entry>
    <entry key="InvalidControllerInfo">Figure コントローラー作成中の内部エラー。</entry>
    <entry key="InvalidCurrentAxesHandle">{0} のハンドルが ''CurrentAxes'' プロパティに渡されました。有効な Axes ハンドルが必要です。</entry>
    <entry key="InvalidDragRectColumns">ドラッグ四角形は、{0,number,integer} ではなく 4 列をもつ必要があります</entry>
    <entry key="InvalidParent">Figure の親はルートでなければなりません。</entry>
    <entry key="InvalidRendererBuffer">内部エラー。レンダー バッファーが存在しません。</entry>
    <entry key="Newplot">newplot は Axes のハンドルを返しませんでした。</entry>
    <entry key="NotDockable">Web figures with menus or toolbar cannot be docked.</entry>
    <entry key="NotDockableWarning">メニューまたはツール バーをもつ Web 上の Figure はドッキングできません。Figure を自動的にドックから出します。</entry>
    <entry key="Pointer">フル十字形ポインターは、サポートされなくなりました。代わりに十字形ポインターを使用してください。</entry>
    <entry key="PrintTemplate">PrintTemplate は適切に初期化されていません</entry>
    <entry key="RbboxColumns">rbbox 四角形には、{0,number,integer} 列ではなく 4 列が含まれていなければなりません。</entry>
    <entry key="RbboxFirstArg">rbbox の最初の引数は有効な四角形でなければなりません。</entry>
    <entry key="RbboxRows">rbbox 四角形には、{0,number,integer} 行ではなく 1 行が含まれていなければなりません。</entry>
    <entry key="RbboxSecondArg">rbbox の 2 番目の引数は有効な点でなければなりません。</entry>
    <entry key="RecursionOnClose">コールバックは、CLOSE を再帰的に呼び出しています。このメッセージを表示しないようにするには DELETE を使用してください。</entry>
    <entry key="Renderer">{0,number,integer} x {1,number,integer} の Z-buffer を描画するためのメモリが足りません</entry>
    <entry key="SetDefaultButtonChildOfFigure">指定した uicontrol は、指定した Figure の子でなければなりません。</entry>
    <entry key="SetDefaultButtonInputArgument">setDefaultButton は、最初の引数として Figure ハンドルを、2 番目の引数として uicontrol ハンドルを指定して呼び出さなければなりません。</entry>
    <entry key="SetDefaultButtonInvalidFigure">setDefaultButton は、有効な uicontrol を含んでいる Figure で呼び出さなければなりません。</entry>
    <entry key="SetDefaultButtonNullInput">setDefaultButton は、有効な uicontrol を含んでいる Figure で呼び出さなければなりません。</entry>
    <entry key="SetDefaultButtonPlatform">setDefaultButton はこのプラットフォームにサポートされていません</entry>
    <entry key="SetDefaultButtonPushButton">setDefaultButton は、スタイルが ''pushbutton'' の uicontrol のみを受け入れます。</entry>
    <entry key="SetDefaultButtonUicontrol">setDefaultButton は、有効な uicontrol を含んでいる Figure で呼び出さなければなりません。</entry>
    <entry key="SetDockControlsOff">WindowStyle が ''docked'' の間は DockControls を ''off'' に設定できません。</entry>
    <entry key="SetDockControlsOn">非 Java の Figure では、DockControls を ''on'' に設定できません。</entry>
    <entry key="SetOuterPosition">WindowStyle が ''docked'' の間は OuterPosition を設定できません</entry>
    <entry key="SetPaperSize">幅と高さは 0 より大きくなければなりません。</entry>
    <entry key="SetPointerShapeCData">PointerShapeCData は 16 行 16 列でなければなりません。</entry>
    <entry key="SetPointerShapeHotSpot">PointerShapeHotSpot は 1 行 2 列でなければなりません。</entry>
    <entry key="SetPosition">WindowStyle が ''docked'' の間は Position を設定できません</entry>
    <entry key="SetResize">WindowStyle が ''docked'' の間は Resize を ''off'' に設定できません。</entry>
    <entry key="SetXDisplay">ディスプレイを開けません</entry>
    <entry key="UnableToSetRendererToOpenGL">この Figure では Renderer を OpenGL に設定できません。</entry>
    <entry key="Units">文字のサイズを計算できませんでした。Figure の位置が正しくない可能性があります。</entry>
    <entry key="UnsupportedToolsStyle">This ToolsStyle is not supported for this figure.</entry>
    <entry key="Waitforbuttonpress">Waitforbuttonpress は、MATLAB をエンジンとして使う場合は利用できません。</entry>
    <entry key="XDisplay">XDisplay を設定できません</entry>
    <entry key="drawnowTicToc">''tic'' オプションと ''toc'' オプションを併用することはできません。</entry>
    <entry key="webfigureredraw">Figure ハンドルが必要です。</entry>
    <entry key="NonResizableFiguresCannotMaximize">''Resize'' が ''off'' の場合、''最大化された'' ウィンドウ状態はサポートされません。</entry>
    <entry key="DockedFiguresCannotSetWindowState">ドッキングされた Figure では ''WindowState'' はサポートされません。</entry>
    <entry key="InvalidFitToContentAnchor">アンカー オプションは 'center' または 'topleft' でなければなりません。</entry>
    <entry key="FitToContentCalledWithNoGrid">fitToContent を使用して Figure のサイズを変更するには、Figure に GridLayout オブジェクトが含まれていなければなりません。</entry>
  </message>
</rsccat>
