<?xml version="1.0" encoding="utf-8"?>
<rsccat locale="en_US" product="MATLAB" version="1.0">
   <message>
      <entry key="FaceColor">Face Color</entry>
      <entry key="EdgeColor">Edge Color</entry>
      <entry key="TextColor">Text Color</entry>
      <entry key="Font">Font</entry>
      <entry key="Bold">Bold</entry>
      <entry key="Italic">Italic</entry>
      <entry key="AlignLeft">Align Left</entry>
      <entry key="AlignCenter">Align Center</entry>
      <entry key="AlignRight">Align Right</entry>
      <entry key="Color">Color</entry>
      <entry key="BackgroundColor">Background Color</entry>
      <entry key="HeadColor">Head Color</entry>
   </message>
</rsccat>
